evm_cfg_builder/__init__.py
evm_cfg_builder/__main__.py
evm_cfg_builder/known_hashes.py
evm_cfg_builder/value_set_analysis.py
evm_cfg_builder/cfg/__init__.py
evm_cfg_builder/cfg/basic_block.py
evm_cfg_builder/cfg/function.py
evm_cfg_builder-0.2.0.dist-info/LICENSE
evm_cfg_builder-0.2.0.dist-info/METADATA
evm_cfg_builder-0.2.0.dist-info/WHEEL
evm_cfg_builder-0.2.0.dist-info/entry_points.txt
evm_cfg_builder-0.2.0.dist-info/top_level.txt
evm_cfg_builder-0.2.0.dist-info/RECORD
