Metadata-Version: 2.1
Name: evm-cfg-builder
Version: 0.2.0
Summary: EVM cfg builder written in Python 3.
Home-page: https://github.com/trailofbits/evm_cfg_builder
Author: Trail of Bits
License: AGPL-3.0
Platform: UNKNOWN
Requires-Python: >=3.6
Requires-Dist: pyevmasm (>=0.1.1)
